MANIFEST.in
README.md
setup.py
dhivehi_nlp/__init__.py
dhivehi_nlp/_helpers.py
dhivehi_nlp/corpus.py
dhivehi_nlp/dictionary.py
dhivehi_nlp/language_models.py
dhivehi_nlp/stemmer.py
dhivehi_nlp/stopwords.py
dhivehi_nlp/tagger.py
dhivehi_nlp/tokenizer.py
dhivehi_nlp/trigram_similarity.py
dhivehi_nlp.egg-info/PKG-INFO
dhivehi_nlp.egg-info/SOURCES.txt
dhivehi_nlp.egg-info/dependency_links.txt
dhivehi_nlp.egg-info/top_level.txt
dhivehi_nlp/data/dhivehi_nlp.db
test/__init__.py
test/test_corpus.py
test/test_dictionary.py
test/test_language_models.py
test/test_stemmer.py
test/test_stopwords.py
test/test_tagger.py
test/test_tokenizer.py
test/test_trigram_similarity.py