Metadata-Version: 2.1
Name: dhivehi-nlp
Version: 1.0.9
Summary: Natural language processing tools for the Dhivehi language.
Home-page: https://github.com/mismaah/dhivehi-nlp
Author: Mismaah Abdulla
Author-email: mismaahabdulla@gmail.com
License: UNKNOWN
Platform: UNKNOWN
Classifier: Programming Language :: Python :: 3
Classifier: License :: OSI Approved :: MIT License
Classifier: Operating System :: OS Independent
Requires-Python: >=3.6
